alb_listener_rule/__init__.py
alb_listener_rule/alb_listener_rule_stack.py
alb_listener_rule-0.1.1.dist-info/licenses/LICENSE
alb_listener_rule-0.1.1.dist-info/METADATA
alb_listener_rule-0.1.1.dist-info/WHEEL
alb_listener_rule-0.1.1.dist-info/top_level.txt
alb_listener_rule-0.1.1.dist-info/RECORD
